README.rst
setup.py
girlfriends/__init__.py
girlfriends/config.py
girlfriends/crop_wechat.py
girlfriends/error_code.py
girlfriends.egg-info/PKG-INFO
girlfriends.egg-info/SOURCES.txt
girlfriends.egg-info/dependency_links.txt
girlfriends.egg-info/top_level.txt
girlfriends.egg-info/zip-safe