Metadata-Version: 1.1
Name: girlfriends
Version: 1.0.2
Summary: a python liberaries  for girlfriends tutorial.
Home-page: http://www.rocyuan.com/
Author: rocyuan
Author-email: admin@rocyuan.com
License: MIT
Keywords: python girlfriends api
Platform: UNKNOWN
Classifier: License :: OSI Approved :: MIT License
Classifier: Programming Language :: Python
Classifier: Intended Audience :: Developers
Classifier: Operating System :: OS Independent
